client/__init__.py
client/launcher.py
lib/__init__.py
lib/credentials.py
lib/opts.py
lib/snwtrans.py
lib/utils.py
lib/commands/__init__.py
lib/commands/docker.py
lib/commands/entity.py
lib/commands/group.py
lib/commands/intersection.py
lib/commands/model.py
lib/commands/permission.py
lib/commands/resource.py
lib/commands/role.py
lib/commands/service.py
lib/commands/share.py
lib/commands/tag.py
lib/commands/task.py
lib/commands/user.py
lib/commands/vocab.py
snw-2.12.6.data/scripts/snw
snw-2.12.6.dist-info/METADATA
snw-2.12.6.dist-info/WHEEL
snw-2.12.6.dist-info/top_level.txt
snw-2.12.6.dist-info/RECORD
