Metadata-Version: 2.4
Name: snw
Version: 2.12.6
Summary: snw client tool
Home-page: http://www.systransoft.com
Author: Jean Senellart
Author-email: jean.senellart@systrangroup.com
Requires-Dist: python-pcre
Requires-Dist: configparser
Requires-Dist: enlighten
Requires-Dist: prettytable
Requires-Dist: requests
Requires-Dist: six>=1.14.0
Requires-Dist: setuptools
Requires-Dist: jsonschema
Requires-Dist: packaging>=17.0
Requires-Dist: semver
Dynamic: author
Dynamic: author-email
Dynamic: home-page
Dynamic: requires-dist
Dynamic: summary
